{
  "title": "About The Brand - SkyyRose",
  "type": "page",
  "version": "0.4",
  "metadata": {
    "title": "About The Brand",
    "created_at": "2025-12-16",
    "generator": "DevSkyy ElementorTemplateGenerator",
    "brand": "SkyyRose",
    "elementor_version": "3.32+",
    "theme_compatibility": "Shoptimizer 2.9.0"
  },
  "settings": {
    "template": "elementor_header_footer",
    "hide_title": "yes"
  },
  "content": [
    {
      "id": "hero_section",
      "elType": "section",
      "settings": {
        "layout": "full_width",
        "min_height": { "unit": "vh", "size": 60 },
        "background_background": "classic",
        "background_image": { "url": "/wp-content/uploads/about/brand-hero.jpg" },
        "background_position": "center center",
        "background_size": "cover",
        "background_overlay_color": "rgba(13,13,13,0.7)",
        "padding": { "unit": "px", "top": 150, "bottom": 150 }
      },
      "elements": [
        {
          "id": "hero_col",
          "elType": "column",
          "settings": { "_column_size": 100 },
          "elements": [
            {
              "id": "hero_title",
              "elType": "widget",
              "widgetType": "heading",
              "settings": {
                "title": "Our Story",
                "header_size": "h1",
                "align": "center",
                "title_color": "#D4AF37",
                "typography_font_family": "Playfair Display",
                "typography_font_size": { "unit": "px", "size": 64 }
              }
            },
            {
              "id": "hero_subtitle",
              "elType": "widget",
              "widgetType": "text-editor",
              "settings": {
                "editor": "<p>Where Love Meets Luxury — Oakland, California</p>",
                "align": "center",
                "text_color": "#F5F5F0",
                "typography_font_family": "Montserrat"
              }
            }
          ]
        }
      ]
    },
    {
      "id": "brand_story_section",
      "elType": "section",
      "settings": {
        "layout": "boxed",
        "structure": "20",
        "background_color": "#0D0D0D",
        "padding": { "unit": "px", "top": 100, "bottom": 100 }
      },
      "elements": [
        {
          "id": "story_image_col",
          "elType": "column",
          "settings": { "_column_size": 50 },
          "elements": [
            {
              "id": "founder_image",
              "elType": "widget",
              "widgetType": "image",
              "settings": {
                "image": { "url": "/wp-content/uploads/about/founder.jpg" },
                "image_size": "large",
                "align": "center",
                "border_radius": { "unit": "px", "top": 10, "right": 10, "bottom": 10, "left": 10 }
              }
            }
          ]
        },
        {
          "id": "story_text_col",
          "elType": "column",
          "settings": { "_column_size": 50, "align": "center", "justify_content": "center" },
          "elements": [
            {
              "id": "story_heading",
              "elType": "widget",
              "widgetType": "heading",
              "settings": {
                "title": "Founded on Love",
                "header_size": "h2",
                "title_color": "#D4AF37",
                "typography_font_family": "Playfair Display",
                "typography_font_size": { "unit": "px", "size": 36 }
              }
            },
            {
              "id": "story_text",
              "elType": "widget",
              "widgetType": "text-editor",
              "settings": {
                "editor": "<p>SkyyRose was born from a passion for self-expression and a belief that fashion should tell a story. Each piece in our collection is designed to empower, inspire, and celebrate the unique beauty within every person.</p><p>From our Oakland studio, we craft garments that blend timeless elegance with contemporary edge — creating pieces that become part of your personal narrative.</p>",
                "text_color": "#F5F5F0",
                "typography_font_family": "Montserrat",
                "typography_font_size": { "unit": "px", "size": 16 },
                "typography_line_height": { "unit": "em", "size": 1.8 }
              }
            }
          ]
        }
      ]
    },
    {
      "id": "timeline_section",
      "elType": "section",
      "settings": {
        "layout": "boxed",
        "background_color": "#1A1A1A",
        "padding": { "unit": "px", "top": 80, "bottom": 80 }
      },
      "elements": [
        {
          "id": "timeline_col",
          "elType": "column",
          "settings": { "_column_size": 100 },
          "elements": [
            {
              "id": "timeline_heading",
              "elType": "widget",
              "widgetType": "heading",
              "settings": {
                "title": "Our Journey",
                "header_size": "h2",
                "align": "center",
                "title_color": "#D4AF37",
                "typography_font_family": "Playfair Display"
              }
            },
            {
              "id": "timeline_widget",
              "elType": "widget",
              "widgetType": "timeline",
              "settings": {
                "items": [
                  { "title": "2020", "content": "SkyyRose founded in Oakland, California", "icon": "fa fa-star" },
                  { "title": "2021", "content": "Launch of BLACK ROSE collection", "icon": "fa fa-gem" },
                  { "title": "2022", "content": "SIGNATURE collection debuts", "icon": "fa fa-crown" },
                  { "title": "2023", "content": "LOVE HURTS collection breaks records", "icon": "fa fa-heart" },
                  { "title": "2024", "content": "3D virtual shopping experience launches", "icon": "fa fa-cube" }
                ],
                "title_color": "#D4AF37",
                "content_color": "#F5F5F0",
                "icon_color": "#D4AF37"
              }
            }
          ]
        }
      ]
    },
    {
      "id": "values_section",
      "elType": "section",
      "settings": {
        "layout": "boxed",
        "structure": "40",
        "background_color": "#0D0D0D",
        "padding": { "unit": "px", "top": 100, "bottom": 100 }
      },
      "elements": [
        {
          "id": "value_1_col",
          "elType": "column",
          "settings": { "_column_size": 25 },
          "elements": [
            {
              "id": "value_1",
              "elType": "widget",
              "widgetType": "icon-box",
              "settings": {
                "selected_icon": { "value": "fas fa-gem" },
                "title": "Quality",
                "description": "Premium materials, expert craftsmanship",
                "title_color": "#D4AF37",
                "description_color": "#F5F5F0",
                "primary_color": "#D4AF37",
                "position": "top"
              }
            }
          ]
        },
        {
          "id": "value_2_col",
          "elType": "column",
          "settings": { "_column_size": 25 },
          "elements": [
            {
              "id": "value_2",
              "elType": "widget",
              "widgetType": "icon-box",
              "settings": {
                "selected_icon": { "value": "fas fa-leaf" },
                "title": "Sustainability",
                "description": "Ethical sourcing, mindful production",
                "title_color": "#D4AF37",
                "description_color": "#F5F5F0",
                "primary_color": "#D4AF37",
                "position": "top"
              }
            }
          ]
        },
        {
          "id": "value_3_col",
          "elType": "column",
          "settings": { "_column_size": 25 },
          "elements": [
            {
              "id": "value_3",
              "elType": "widget",
              "widgetType": "icon-box",
              "settings": {
                "selected_icon": { "value": "fas fa-heart" },
                "title": "Empowerment",
                "description": "Fashion that celebrates you",
                "title_color": "#D4AF37",
                "description_color": "#F5F5F0",
                "primary_color": "#D4AF37",
                "position": "top"
              }
            }
          ]
        },
        {
          "id": "value_4_col",
          "elType": "column",
          "settings": { "_column_size": 25 },
          "elements": [
            {
              "id": "value_4",
              "elType": "widget",
              "widgetType": "icon-box",
              "settings": {
                "selected_icon": { "value": "fas fa-users" },
                "title": "Community",
                "description": "Built by dreamers, for dreamers",
                "title_color": "#D4AF37",
                "description_color": "#F5F5F0",
                "primary_color": "#D4AF37",
                "position": "top"
              }
            }
          ]
        }
      ]
    },
    {
      "id": "press_section",
      "elType": "section",
      "settings": {
        "layout": "boxed",
        "background_color": "#1A1A1A",
        "padding": { "unit": "px", "top": 80, "bottom": 80 }
      },
      "elements": [
        {
          "id": "press_col",
          "elType": "column",
          "settings": { "_column_size": 100 },
          "elements": [
            {
              "id": "press_heading",
              "elType": "widget",
              "widgetType": "heading",
              "settings": {
                "title": "As Seen In",
                "header_size": "h3",
                "align": "center",
                "title_color": "#D4AF37"
              }
            },
            {
              "id": "press_logos",
              "elType": "widget",
              "widgetType": "image-carousel",
              "settings": {
                "carousel": [
                  { "url": "/wp-content/uploads/press/vogue.png" },
                  { "url": "/wp-content/uploads/press/elle.png" },
                  { "url": "/wp-content/uploads/press/harpers.png" },
                  { "url": "/wp-content/uploads/press/cosmopolitan.png" }
                ],
                "slides_to_show": "4",
                "autoplay": "yes",
                "infinite": "yes"
              }
            }
          ]
        }
      ]
    }
  ],
  "responsive": {
    "tablet": { "values_section": { "structure": "20" } },
    "mobile": { "values_section": { "structure": "10" }, "brand_story_section": { "structure": "10" } }
  }
}

